GeoAPI/Geocoding.py
GeoAPI/String_Match.py
GeoAPI/__init__.py
GeoAPI/dispersion.py
GeoAPI/open_addresses.py
GeoAPI/point_validation.py
GeoAPI/preprocessing.py
GeoAPI/utils.py
GeoAPI/visualization.py
GeoAPI/Data/Tabela_abreviações.csv
GeoAPI/Data/__init__.py
GeoAPI/Data/data.csv
GeoAPI/Data/data2.csv
GeoAPI/Data/data_pelias.csv
GeoAPI/Data/id29-clientes-mapeado_consolidado.csv
GeoAPI/Data/out.csv
GeoAPI/Data/relatorio.xls
GeoAPI/Data/visualization.py
geoapidata-0.0.19.dist-info/AUTHORS
geoapidata-0.0.19.dist-info/LICENSE
geoapidata-0.0.19.dist-info/METADATA
geoapidata-0.0.19.dist-info/WHEEL
geoapidata-0.0.19.dist-info/top_level.txt
geoapidata-0.0.19.dist-info/RECORD
