Metadata-Version: 2.1
Name: geoapidata
Version: 0.0.19
Summary: GeoAPI do TerraLab
Home-page: UNKNOWN
Author: TerraLab
License: UNKNOWN
Platform: UNKNOWN
License-File: LICENSE
License-File: AUTHORS
Requires-Dist: geopandas
Requires-Dist: unidecode
Requires-Dist: sparse-dot-topn
Requires-Dist: dash
Requires-Dist: pandas
Requires-Dist: plotly
Requires-Dist: geopy (==2.2.0)
Requires-Dist: sklearn
Requires-Dist: numpy
Requires-Dist: scipy
Requires-Dist: matplotlib
Requires-Dist: requests
